setup.py
shutter/__init__.py
shutter/shutter.py
shutter.egg-info/PKG-INFO
shutter.egg-info/SOURCES.txt
shutter.egg-info/dependency_links.txt
shutter.egg-info/top_level.txt