Metadata-Version: 1.1
Name: shutter
Version: 0.0.7
Summary: ctypes interface for libgphoto2
Home-page: UNKNOWN
Author: bitcraft
Author-email: leif.theden@gmail.com
License: GPLv3
Keywords: gphoto,libgphoto2,capture,shutter
Platform: UNKNOWN
Classifier: Intended Audience :: Developers
Classifier: Development Status :: 3 - Alpha
Classifier: Topic :: Multimedia :: Graphics :: Capture :: Digital Camera
Classifier: Programming Language :: Python :: 2.7
Requires: six
